{
  "production": {
    "environment": "production",
    "deployment_strategy": "blue_green",
    "health_checks": {
      "enabled": true,
      "interval_seconds": 30,
      "timeout_seconds": 10,
      "unhealthy_threshold": 3,
      "healthy_threshold": 2
    },
    "scaling": {
      "min_instances": 2,
      "max_instances": 10,
      "target_cpu_percent": 70,
      "target_memory_percent": 80
    },
    "monitoring": {
      "enabled": true,
      "metrics": [
        "cpu",
        "memory",
        "latency",
        "error_rate",
        "trading_volume"
      ],
      "alerting": {
        "slack_webhook": null,
        "email_alerts": true,
        "pagerduty_integration": false
      }
    },
    "security": {
      "api_key_rotation": "monthly",
      "encryption_at_rest": true,
      "encryption_in_transit": true,
      "ip_whitelist": true,
      "rate_limiting": {
        "enabled": true,
        "requests_per_minute": 1000
      }
    },
    "backup": {
      "enabled": true,
      "frequency": "daily",
      "retention_days": 30,
      "offsite_backup": true
    }
  },
  "infrastructure": {
    "provider": "aws",
    "region": "us-east-1",
    "instance_type": "t3.medium",
    "database": {
      "type": "postgresql",
      "version": "14",
      "instance_class": "db.t3.micro",
      "multi_az": true
    },
    "storage": {
      "type": "ebs",
      "size_gb": 100,
      "iops": 3000
    },
    "cdn": {
      "enabled": true,
      "provider": "cloudfront"
    },
    "load_balancer": {
      "type": "application",
      "ssl_certificate": true
    }
  },
  "cost_estimates": {
    "monthly_infrastructure": 150,
    "monthly_monitoring": 50,
    "monthly_support": 200,
    "total_monthly_cost": 400
  }
}